{
    "type": 0,
    "size": { "w": 1346, "h": 1452 },
    "objects": [
        {
            "w": 886, "h": 84,
            "x": 230, "y": 90,
            "image": "/assets/images/theater/01/screen/024.svg"
        },
        {
            "w": 38, "h": 104,
            "x": 158, "y": 1234,
            "image": "/assets/images/theater/01/door/002.svg"
        },
        {
            "w": 104, "h": 38,
            "x": 210, "y": 1324,
            "image": "/assets/images/theater/01/door/001.svg"
        },
        {
            "w": 104, "h": 38,
            "x": 621, "y": 1324,
            "image": "/assets/images/theater/01/door/001.svg"
        },
        {
            "w": 104, "h": 38,
            "x": 1032, "y": 1324,
            "image": "/assets/images/theater/01/door/001.svg"
        }
    ],
    "seatStart": { "x": 210, "y": 204 },
    "map": [
        [0, 0, 0, 0, 0, 0, 0, 0, 0, 6, 0, 0, 0, 0, 0, 0, 0, 0, 0, 0],
        [0, 0, 1, 1, 1, 1, 1, 1, 1, 4, 1, 1, 1, 1, 1, 1, 1, 1, 0, 0],
        [0, 0, 1, 1, 1, 1, 1, 1, 1, 4, 1, 1, 1, 1, 1, 1, 1, 1, 0, 0],
        [0, 0, 1, 1, 1, 1, 1, 1, 1, 4, 1, 1, 1, 1, 1, 1, 1, 1, 0, 0],
        [0, 0, 1, 1, 1, 1, 1, 1, 1, 4, 1, 1, 1, 1, 1, 1, 1, 1, 0, 0],
        [1, 1, 1, 1, 1, 1, 1, 1, 1, 4, 1, 1, 1, 1, 1, 1, 1, 1, 1, 1],
        [1, 1, 1, 1, 1, 1, 1, 1, 1, 4, 1, 1, 1, 1, 1, 1, 1, 1, 1, 1],
        [1, 1, 1, 1, 1, 1, 1, 1, 1, 4, 1, 1, 1, 1, 1, 1, 1, 1, 1, 1],
        [1, 1, 1, 1, 1, 1, 1, 1, 1, 4, 1, 1, 1, 1, 1, 1, 1, 1, 1, 1],
        [1, 1, 1, 1, 1, 1, 1, 1, 1, 4, 1, 1, 1, 1, 1, 1, 1, 1, 1, 1],
        [1, 1, 1, 1, 1, 1, 1, 1, 1, 4, 1, 1, 1, 1, 1, 1, 1, 1, 1, 1],
        [1, 1, 1, 1, 1, 1, 1, 1, 1, 4, 1, 1, 1, 1, 1, 1, 1, 1, 1, 1],
        [1, 1, 1, 1, 1, 1, 1, 1, 1, 4, 1, 1, 1, 1, 1, 1, 1, 1, 1, 1],
        [1, 1, 1, 1, 1, 1, 1, 1, 1, 4, 1, 1, 1, 1, 1, 1, 1, 1, 1, 1],
        [1, 1, 1, 1, 1, 1, 1, 1, 1, 4, 1, 1, 1, 1, 1, 1, 1, 1, 1, 1]
    ],
    "special": [],
    "hc": [],
    "pair": [],
    "style": "<style>.column-object{ top: 220px !important; } .line-object-0{ display:none; }</style>"
}
